pypmed/__init__.py
pypmed/apis.py
pypmed/checks.py
pypmed/filters.py
pypmed/parsers.py
pypmed-0.1.8.dist-info/LICENSE
pypmed-0.1.8.dist-info/METADATA
pypmed-0.1.8.dist-info/WHEEL
pypmed-0.1.8.dist-info/RECORD
