Metadata-Version: 2.1
Name: pypmed
Version: 0.1.8
Summary: python wrapper for pubmed apis --> https://eutils.ncbi.nlm.nih.gov/entrez/eutils/esearch.fcgi/
Home-page: https://github.com/jermwatt/pypmed
License: MIT
Author: Jeremy Watt
Author-email: jermwatt@gmail.com
Requires-Python: >=3.9.1,<3.11
Classifier: License :: OSI Approved :: MIT License
Classifier: Programming Language :: Python :: 3
Classifier: Programming Language :: Python :: 3.10
Requires-Dist: rapidfuzz (>=3.0.0,<4.0.0)
Requires-Dist: requests (>=2.28.2,<3.0.0)
